ACME/__init__.py
ACME/__main__.py
ACME/acme.txt
ACME/errors.py
ACME/payment.json
ACME/payment_class.py
ACME/utils.py
test/__init__.py
test/test_acme.py
acme_ioet_orestes-0.0.2.dist-info/LICENSE
acme_ioet_orestes-0.0.2.dist-info/METADATA
acme_ioet_orestes-0.0.2.dist-info/WHEEL
acme_ioet_orestes-0.0.2.dist-info/entry_points.txt
acme_ioet_orestes-0.0.2.dist-info/top_level.txt
acme_ioet_orestes-0.0.2.dist-info/RECORD
