Metadata-Version: 2.1
Name: acme-ioet-orestes
Version: 0.0.2
Summary: App to calculate salary of Acme's Employees
Home-page: https://github.com/orestes7054/acme
Author: Orestes Olivera
Author-email: orestes.om@gmail.com
License: MIT
Project-URL: Homepage, https://github.com/orestes7054/acme
Project-URL: Source Code, https://github.com/orestes7054/acme
Platform: UNKNOWN
Classifier: Programming Language :: Python :: 3.9
Classifier: License :: OSI Approved :: MIT License
Requires-Python: >=3.6
